{"layers": [{"spans": [{"start": 0, "end": 5}, {"start": 6, "end": 12}, {"start": 12, "end": 13}], "name": "words", "_base": "words", "ambiguous": false, "attributes": [], "parent": null, "enveloping": null}, {"spans": [], "name": "normalized_words", "_base": "words", "ambiguous": false, "attributes": ["normal"], "parent": "words", "enveloping": null}, {"spans": [[{"root": "ööbik", "lemma": "ööbik", "ending": "0", "start": 0, "_index_": 0, "root_tokens": ["ööbik"], "partofspeech": "S", "clitic": "", "form": "sg n", "end": 5}], [{"root": "laul", "lemma": "laulma", "ending": "b", "start": 6, "_index_": 1, "root_tokens": ["laul"], "partofspeech": "V", "clitic": "", "form": "b", "end": 12}], [{"root": ".", "lemma": ".", "ending": "", "start": 12, "_index_": 2, "root_tokens": ["."], "partofspeech": "Z", "clitic": "", "form": "", "end": 13}]], "name": "morph_analysis", "_base": "words", "ambiguous": true, "attributes": ["lemma", "root", "root_tokens", "ending", "clitic", "form", "partofspeech"], "parent": "words", "enveloping": null}], "text": "Ööbik laulab."}